Data_Prep_Kit_SM/DataKit.py
Data_Prep_Kit_SM/__init__.py
Data_Prep_Kit_SM-0.1.0.dist-info/METADATA
Data_Prep_Kit_SM-0.1.0.dist-info/WHEEL
Data_Prep_Kit_SM-0.1.0.dist-info/top_level.txt
Data_Prep_Kit_SM-0.1.0.dist-info/RECORD
